glowdb/__init__.py
glowdb/client.py
glowdb/models.py
glowdb/rpc_server.py
glowdb/utils.py
glowdb-0.0.2.dist-info/METADATA
glowdb-0.0.2.dist-info/WHEEL
glowdb-0.0.2.dist-info/entry_points.txt
glowdb-0.0.2.dist-info/RECORD
