Metadata-Version: 2.1
Name: glowdb
Version: 0.0.2
Summary: A fast and efficient key/value store or document database which can work as a drop-in replacement for DynamoDB or MongoDB.
Author: Oscar Bahamonde
Author-email: oscar.bahamonde@indiecloud.co
Requires-Python: >=3.10,<4.0
Classifier: Programming Language :: Python :: 3
Classifier: Programming Language :: Python :: 3.10
Classifier: Programming Language :: Python :: 3.11
Classifier: Programming Language :: Python :: 3.12
Requires-Dist: base64c (>=0.0.8,<0.0.9)
Requires-Dist: click (>=8.1.7,<9.0.0)
Requires-Dist: orjson (>=3.10.7,<4.0.0)
Requires-Dist: pydantic (>=2.9.2,<3.0.0)
Requires-Dist: rocksdict (>=0.3.23,<0.4.0)
Requires-Dist: websockets (>=13.1,<14.0)
